Workbook

Sheet Empresa 1 - Serviços
A1: Ano | B1: Receita Total | C1: Receita via Cartão de Crédito | D1: Receita via Boletos | E1: Receita via Pix | F1: Receita via Transferências | G1: Despesas com Empregados | H1: Despesas com Aluguel | I1: Despesas com Energia | J1: Despesas com Água | K1: Despesas com Fornecedores | L1: Despesas Operacionais | M1: Total de Despesas | N1: Saldo do Mês | O1: Saldo Acumulado
A2: 44197 | B2: 218904.88 | C2: 32835.732 | D2: 120397.68 | E2: 65671.464 | F2: 21890.488 | G2: 90000 | H2: 5000 | I2: 1500 | J2: 500 | K2: 65671.464 | L2: 32835.732 | M2: 195507.2 | N2: 23397.683 | O2: 23397.683
A3: 44228 | B3: 209147.98 | C3: 31372.196 | D3: 115031.39 | E3: 62744.393 | F3: 20914.798 | G3: 90000 | H3: 5000 | I3: 1500 | J3: 500 | K3: 62744.393 | L3: 31372.196 | M3: 191116.59 | N3: 18031.386 | O3: 41429.07
A4: 44256 | B4: 232476.98 | C4: 34871.547 | D4: 127862.34 | E4: 69743.094 | F4: 23247.698 | G4: 90000 | H4: 5000 | I4: 1500 | J4: 500 | K4: 69743.094 | L4: 34871.547 | M4: 201614.64 | N4: 30862.339 | O4: 72291.409
A5: 44287 | B5: 244923.29 | C5: 36738.493 | D5: 134707.81 | E5: 73476.986 | F5: 24492.329 | G5: 90000 | H5: 5000 | I5: 1500 | J5: 500 | K5: 73476.986 | L5: 36738.493 | M5: 207215.48 | N5: 37707.808 | O5: 109999.22
A6: 44317 | B6: 268690.1 | C6: 40303.515 | D6: 147779.56 | E6: 80607.031 | F6: 26869.01 | G6: 90000 | H6: 5000 | I6: 1500 | J6: 500 | K6: 80607.031 | L6: 40303.515 | M6: 217910.55 | N6: 50779.556 | O6: 160778.77
A7: 44348 | B7: 292707.09 | C7: 43906.064 | D7: 160988.9 | E7: 87812.128 | F7: 29270.709 | G7: 90000 | H7: 5000 | I7: 1500 | J7: 500 | K7: 87812.128 | L7: 43906.064 | M7: 228718.19 | N7: 63988.902 | O7: 224767.67
A8: 44378 | B8: 283012.74 | C8: 42451.91 | D8: 155657 | E8: 84903.821 | F8: 28301.274 | G8: 90000 | H8: 5000 | I8: 1500 | J8: 500 | K8: 84903.821 | L8: 42451.91 | M8: 224355.73 | N8: 58657.005 | O8: 283424.68
A9: 44409 | B9: 273193.29 | C9: 40978.993 | D9: 150256.31 | E9: 81957.986 | F9: 27319.329 | G9: 90000 | H9: 5000 | I9: 1500 | J9: 500 | K9: 81957.986 | L9: 40978.993 | M9: 219936.98 | N9: 53256.309 | O9: 336680.99
A10: 44440 | B10: 263248.75 | C10: 39487.313 | D10: 144786.81 | E10: 78974.626 | F10: 26324.875 | G10: 90000 | H10: 5000 | I10: 1500 | J10: 500 | K10: 78974.626 | L10: 39487.313 | M10: 215461.94 | N10: 47786.814 | O10: 384467.8
A11: 44470 | B11: 253179.13 | C11: 37976.869 | D11: 139248.52 | E11: 75953.738 | F11: 25317.913 | G11: 90000 | H11: 5000 | I11: 1500 | J11: 500 | K11: 75953.738 | L11: 37976.869 | M11: 210930.61 | N11: 42248.52 | O11: 426716.32
A12: 44501 | B12: 231413.73 | C12: 34712.059 | D12: 127277.55 | E12: 69424.119 | F12: 23141.373 | G12: 90000 | H12: 5000 | I12: 1500 | J12: 500 | K12: 69424.119 | L12: 34712.059 | M12: 201136.18 | N12: 30277.551 | O12: 456993.87
A13: 44531 | B13: 209398.15 | C13: 31409.723 | D13: 115168.98 | E13: 62819.446 | F13: 20939.815 | G13: 90000 | H13: 5000 | I13: 1500 | J13: 500 | K13: 62819.446 | L13: 31409.723 | M13: 191229.17 | N13: 18168.984 | O13: 475162.86
... A37: 45261 | B37: 236417.27 | C37: 35462.59 | D37: 130029.5 | E37: 70925.181 | F37: 23641.727 | G37: 90000 | H37: 5000 | I37: 1500 | J37: 500 | K37: 70925.181 | L37: 35462.59 | M37: 203387.77 | N37: 33029.498 | O37: 1752419.9

Sheet Empresa 2 - Comércio
A1: Ano | B1: Receita Total | C1: Receita via Cartão de Crédito | D1: Receita via Boletos | E1: Receita via Pix | F1: Receita via Transferências | G1: Despesas com Empregados | H1: Despesas com Aluguel | I1: Despesas com Energia | J1: Despesas com Água | K1: Despesas com Fornecedores | L1: Despesas Operacionais | M1: Total de Despesas | N1: Saldo do Mês | O1: Saldo Acumulado
A2: 44197 | B2: 30567.818 | C2: 10698.736 | D2: 6113.5636 | E2: 12227.127 | F2: 1528.3909 | G2: 15000 | H2: 2000 | I2: 800 | J2: 300 | K2: 9170.3455 | L2: 4585.1727 | M2: 31855.518 | N2: -1287.7 | O2: -1287.7
A3: 44228 | B3: 28997.942 | C3: 10149.28 | D3: 5799.5885 | E3: 11599.177 | F3: 1449.8971 | G3: 15000 | H3: 2000 | I3: 800 | J3: 300 | K3: 8699.3827 | L3: 4349.6914 | M3: 31149.074 | N3: -2151.1317 | O3: -3438.8317
A4: 44256 | B4: 32004.506 | C4: 11201.577 | D4: 6400.9011 | E4: 12801.802 | F4: 1600.2253 | G4: 15000 | H4: 2000 | I4: 800 | J4: 300 | K4: 9601.3517 | L4: 4800.6758 | M4: 32502.028 | N4: -497.52189 | O4: -3936.3536
A5: 44287 | B5: 33480.495 | C5: 11718.173 | D5: 6696.0989 | E5: 13392.198 | F5: 1674.0247 | G5: 15000 | H5: 2000 | I5: 800 | J5: 300 | K5: 10044.148 | L5: 5022.0742 | M5: 33166.223 | N5: 314.27203 | O5: -3622.0815
A6: 44317 | B6: 36471.774 | C6: 12765.121 | D6: 7294.3548 | E6: 14588.71 | F6: 1823.5887 | G6: 15000 | H6: 2000 | I6: 800 | J6: 300 | K6: 10941.532 | L6: 5470.7661 | M6: 34512.298 | N6: 1959.4757 | O6: -1662.6059
A7: 44348 | B7: 39454.32 | C7: 13809.012 | D7: 7890.8639 | E7: 15781.728 | F7: 1972.716 | G7: 15000 | H7: 2000 | I7: 800 | J7: 300 | K7: 11836.296 | L7: 5918.1479 | M7: 35854.444 | N7: 3599.8758 | O7: 1937.27
A8: 44378 | B8: 37882.26 | C8: 13258.791 | D8: 7576.4521 | E8: 15152.904 | F8: 1894.113 | G8: 15000 | H8: 2000 | I8: 800 | J8: 300 | K8: 11364.678 | L8: 5682.3391 | M8: 35147.017 | N8: 2735.2432 | O8: 4672.5132
A9: 44409 | B9: 36314.568 | C9: 12710.099 | D9: 7262.9136 | E9: 14525.827 | F9: 1815.7284 | G9: 15000 | H9: 2000 | I9: 800 | J9: 300 | K9: 10894.37 | L9: 5447.1852 | M9: 34441.556 | N9: 1873.0124 | O9: 6545.5256
A10: 44440 | B10: 34751.242 | C10: 12162.935 | D10: 6950.2485 | E10: 13900.497 | F10: 1737.5621 | G10: 15000 | H10: 2000 | I10: 800 | J10: 300 | K10: 10425.373 | L10: 5212.6864 | M10: 33738.059 | N10: 1013.1834 | O10: 7558.709
A11: 44470 | B11: 33192.284 | C11: 11617.299 | D11: 6638.4567 | E11: 13276.913 | F11: 1659.6142 | G11: 15000 | H11: 2000 | I11: 800 | J11: 300 | K11: 9957.6851 | L11: 4978.8426 | M11: 33036.528 | N11: 155.75606 | O11: 7714.465
A12: 44501 | B12: 30131.135 | C12: 10545.897 | D12: 6026.227 | E12: 12052.454 | F12: 1506.5568 | G12: 15000 | H12: 2000 | I12: 800 | J12: 300 | K12: 9039.3405 | L12: 4519.6703 | M12: 31659.011 | N12: -1527.8757 | O12: 6186.5893
A13: 44531 | B13: 27078.72 | C13: 9477.552 | D13: 5415.744 | E13: 10831.488 | F13: 1353.936 | G13: 15000 | H13: 2000 | I13: 800 | J13: 300 | K13: 8123.616 | L13: 4061.808 | M13: 30285.424 | N13: -3206.7039 | O13: 2979.8854
... A37: 45261 | B37: 26135.485 | C37: 9147.4196 | D37: 5227.0969 | E37: 10454.194 | F37: 1306.7742 | G37: 15000 | H37: 2000 | I37: 800 | J37: 300 | K37: 7840.6454 | L37: 3920.3227 | M37: 29860.968 | N37: -3725.4835 | O37: -2473.4938

Sheet Empresa 3 - Indústria
A1: Ano | B1: Receita Total | C1: Receita via Cartão de Crédito | D1: Receita via Boletos | E1: Receita via Pix | F1: Receita via Transferências | G1: Despesas com Empregados | H1: Despesas com Aluguel | I1: Despesas com Energia | J1: Despesas com Água | K1: Despesas com Fornecedores | L1: Despesas Operacionais | M1: Total de Despesas | N1: Saldo do Mês | O1: Saldo Acumulado
A2: 44197 | B2: 888062.16 | C2: 44403.108 | D2: 577240.4 | E2: 222015.54 | F2: 44403.108 | G2: 150000 | H2: 5000 | I2: 1500 | J2: 500 | K2: 266418.65 | L2: 133209.32 | M2: 556627.97 | N2: 331434.19 | O2: 331434.19
A3: 44228 | B3: 840043.37 | C3: 42002.168 | D3: 546028.19 | E3: 210010.84 | F3: 42002.168 | G3: 150000 | H3: 5000 | I3: 1500 | J3: 500 | K3: 252013.01 | L3: 126006.51 | M3: 535019.52 | N3: 305023.85 | O3: 636458.04
A4: 44256 | B4: 924472.71 | C4: 46223.635 | D4: 600907.26 | E4: 231118.18 | F4: 46223.635 | G4: 150000 | H4: 5000 | I4: 1500 | J4: 500 | K4: 277341.81 | L4: 138670.91 | M4: 573012.72 | N4: 351459.99 | O4: 987918.03
A5: 44287 | B5: 964308.64 | C5: 48215.432 | D5: 626800.61 | E5: 241077.16 | F5: 48215.432 | G5: 150000 | H5: 5000 | I5: 1500 | J5: 500 | K5: 289292.59 | L5: 144646.3 | M5: 590938.89 | N5: 373369.75 | O5: 1361287.8
A6: 44317 | B6: 1047405.9 | C6: 52370.294 | D6: 680813.82 | E6: 261851.47 | F6: 52370.294 | G6: 150000 | H6: 5000 | I6: 1500 | J6: 500 | K6: 314221.76 | L6: 157110.88 | M6: 628332.65 | N6: 419073.23 | O6: 1780361
A7: 44348 | B7: 1129741.9 | C7: 56487.096 | D7: 734332.25 | E7: 282435.48 | F7: 56487.096 | G7: 150000 | H7: 5000 | I7: 1500 | J7: 500 | K7: 338922.58 | L7: 169461.29 | M7: 665383.87 | N7: 464358.06 | O7: 2244719.1
A8: 44378 | B8: 1081532.8 | C8: 54076.642 | D8: 702996.35 | E8: 270383.21 | F8: 54076.642 | G8: 150000 | H8: 5000 | I8: 1500 | J8: 500 | K8: 324459.85 | L8: 162229.93 | M8: 643689.78 | N8: 437843.06 | O8: 2682562.1
A9: 44409 | B9: 1033704.4 | C9: 51685.218 | D9: 671907.83 | E9: 258426.09 | F9: 51685.218 | G9: 150000 | H9: 5000 | I9: 1500 | J9: 500 | K9: 310111.31 | L9: 155055.65 | M9: 622166.96 | N9: 411537.39 | O9: 3094099.5
A10: 44440 | B10: 986256.46 | C10: 49312.823 | D10: 641066.7 | E10: 246564.11 | F10: 49312.823 | G10: 150000 | H10: 5000 | I10: 1500 | J10: 500 | K10: 295876.94 | L10: 147938.47 | M10: 600815.41 | N10: 385441.05 | O10: 3479540.6
A11: 44470 | B11: 939189.16 | C11: 46959.458 | D11: 610472.96 | E11: 234797.29 | F11: 46959.458 | G11: 150000 | H11: 5000 | I11: 1500 | J11: 500 | K11: 281756.75 | L11: 140878.37 | M11: 579635.12 | N11: 359554.04 | O11: 3839094.6
A12: 44501 | B12: 850002.35 | C12: 42500.118 | D12: 552501.53 | E12: 212500.59 | F12: 42500.118 | G12: 150000 | H12: 5000 | I12: 1500 | J12: 500 | K12: 255000.71 | L12: 127500.35 | M12: 539501.06 | N12: 310501.29 | O12: 4149595.9
A13: 44531 | B13: 761576.73 | C13: 38078.837 | D13: 495024.88 | E13: 190394.18 | F13: 38078.837 | G13: 150000 | H13: 5000 | I13: 1500 | J13: 500 | K13: 228473.02 | L13: 114236.51 | M13: 499709.53 | N13: 261867.2 | O13: 4411463.1
... A37: 45261 | B37: 679367.55 | C37: 33968.377 | D37: 441588.91 | E37: 169841.89 | F37: 33968.377 | G37: 150000 | H37: 5000 | I37: 1500 | J37: 500 | K37: 203810.26 | L37: 101905.13 | M37: 462715.4 | N37: 216652.15 | O37: 12239658

Sheet Perfil das Empresas
C1: Receita_Ano_1 | D1: Despesa_Ano_1 | E1: Resultado_Ano1 | F1: Receita_Ano_2 | G1: Despesa_Ano_2 | H1: Resultado_Ano2 | I1: Receita_Ano_3 | J1: Despesa_Ano_3 | K1: Resultado_Ano3
A2: Empresa 1 - Serviços: Situação financeira favorável e em crescimento. | C2: =SUM('Empresa 1 - Serviços'!$B$2:$B$13) -> 2980296.1 | D2: =SUM('Empresa 1 - Serviços'!$M$2:$M$13) -> 2505133.2 | E2: =C2-D2 -> 475162.86 | F2: =SUM('Empresa 1 - Serviços'!$B$14:$B$25) -> 3178436.3 | G2: =SUM('Empresa 1 - Serviços'!$M$14:$M$25) -> 2594296.3 | H2: =F2-G2 -> 584139.96 | I2: =SUM('Empresa 1 - Serviços'!$B$26:$B$37) -> 3376576.5 | J2: =SUM('Empresa 1 - Serviços'!$M$26:$M$37) -> 2683459.4 | K2: =I2-J2 -> 693117.06
A3: Empresa 2 - Comércio: Situação relativamente estável, com sinais de quebra de fluxo de caixa. | C3: =SUM('Empresa 2 - Comércio'!$B$2:$B$13) -> 400327.06 | D3: =SUM('Empresa 2 - Comércio'!$M$2:$M$13) -> 397347.18 | E3: =C3-D3 -> 2979.8854 | F3: =SUM('Empresa 2 - Comércio'!$B$14:$B$25) -> 393410 | G3: =SUM('Empresa 2 - Comércio'!$M$14:$M$25) -> 394234.5 | H3: =F3-G3 -> -824.49795 | I3: =SUM('Empresa 2 - Comércio'!$B$26:$B$37) -> 386492.94 | J3: =SUM('Empresa 2 - Comércio'!$M$26:$M$37) -> 391121.82 | K3: =I3-J3 -> -4628.8813
A4: Empresa 3 - Indústria: Situação financeira deficitária, exigindo ajustes na gestão. | C4: =SUM('Empresa 3 - Indústria'!$B$2:$B$13) -> 11446297 | D4: =SUM('Empresa 3 - Indústria'!$M$2:$M$13) -> 7034833.5 | E4: =C4-D4 -> 4411463.1 | F4: =SUM('Empresa 3 - Indústria'!$B$14:$B$25) -> 10843429 | G4: =SUM('Empresa 3 - Indústria'!$M$14:$M$25) -> 6763543.2 | H4: =F4-G4 -> 4079886.1 | I4: =SUM('Empresa 3 - Indústria'!$B$26:$B$37) -> 10240562 | J4: =SUM('Empresa 3 - Indústria'!$M$26:$M$37) -> 6492252.9 | K4: =I4-J4 -> 3748309
